fragfit/__init__.py
fragfit/cli.py
fragfit/version.py
fragfit/adducts/__init__.py
fragfit/adducts/core.py
fragfit/formula/__init__.py
fragfit/formula/core.py
fragfit-0.1.2.dist-info/licenses/AUTHORS.md
fragfit-0.1.2.dist-info/licenses/LICENSE
fragfit-0.1.2.dist-info/METADATA
fragfit-0.1.2.dist-info/WHEEL
fragfit-0.1.2.dist-info/entry_points.txt
fragfit-0.1.2.dist-info/top_level.txt
fragfit-0.1.2.dist-info/RECORD
