Metadata-Version: 2.4
Name: fragfit
Version: 0.1.2
Summary: Utilities for handling chemical formulas and mass spec MS2 fragments
Author-email: Gabe Reder <gk@reder.io>
License: MIT
Project-URL: Homepage, https://github.com/gkreder/fragfit
Project-URL: Issues, https://github.com/gkreder/fragfit/issues
Keywords: mass spectrometry,chemistry,formula,fragment,MS2
Classifier: Programming Language :: Python :: 3
Classifier: Programming Language :: Python :: 3.9
Classifier: Programming Language :: Python :: 3.10
Classifier: Programming Language :: Python :: 3.11
Classifier: Programming Language :: Python :: 3.12
Classifier: License :: OSI Approved :: MIT License
Classifier: Operating System :: OS Independent
Classifier: Topic :: Scientific/Engineering :: Chemistry
Classifier: Topic :: Scientific/Engineering :: Bio-Informatics
Requires-Python: >=3.9
License-File: LICENSE
License-File: AUTHORS.md
Requires-Dist: molmass>=2024.10.25
Requires-Dist: numpy>=1.20.0
Requires-Dist: more-itertools>=10.1.0
Requires-Dist: pandas>=1.3.0
Provides-Extra: dev
Requires-Dist: pytest>=7.0.0; extra == "dev"
Requires-Dist: pytest-cov>=4.0.0; extra == "dev"
Requires-Dist: black>=23.0.0; extra == "dev"
Requires-Dist: isort>=5.12.0; extra == "dev"
Requires-Dist: mypy>=1.0.0; extra == "dev"
Requires-Dist: flake8>=6.0.0; extra == "dev"
Requires-Dist: build>=0.10.0; extra == "dev"
Requires-Dist: twine>=4.0.0; extra == "dev"
Dynamic: license-file
Dynamic: requires-python
